[
  {
    "url": "http://www.aimaker.space/details/?id=143",
    "title": "è±è AI åé ä¹å­ | AI ç¼ç¨æè²_æ³è±¡ååé åæè²",
    "html_path": "/Users/david/david_project/知识库/microblock/download/8f3ae4b501_èè_AI_åé ä¹å__AI_ç¼çæè²_æ³èååé åæè².html",
    "text_path": "/Users/david/david_project/知识库/microblock/download/8f3ae4b501_èè_AI_åé ä¹å__AI_ç¼çæè²_æ³èååé åæè².txt",
    "filename_base": "8f3ae4b501_èè_AI_åé ä¹å__AI_ç¼çæè²_æ³èååé åæè²"
  },
  {
    "url": "https://angilent.github.io/microblocksdoc/",
    "title": "MicroBlocks 中文 Wiki",
    "html_path": "/Users/david/david_project/知识库/microblock/download/6a8ee956d4_MicroBlocks_中文_Wiki.html",
    "text_path": "/Users/david/david_project/知识库/microblock/download/6a8ee956d4_MicroBlocks_中文_Wiki.txt",
    "filename_base": "6a8ee956d4_MicroBlocks_中文_Wiki"
  },
  {
    "url": "https://community.appinventor.mit.edu/t/microblocks-ble-extension/129412",
    "title": "MicroBlocks BLE Extension - Extensions - MIT App Inventor Community",
    "html_path": "/Users/david/david_project/知识库/microblock/download/8ee116379c_MicroBlocks_BLE_Extension_-_Extensions_-_MIT_App_I.html",
    "text_path": "/Users/david/david_project/知识库/microblock/download/8ee116379c_MicroBlocks_BLE_Extension_-_Extensions_-_MIT_App_I.txt",
    "filename_base": "8ee116379c_MicroBlocks_BLE_Extension_-_Extensions_-_MIT_App_I"
  },
  {
    "url": "https://docs.keyestudio.com/projects/FB0004/en/latest/docs/4.Microblocks%20Development%20Environment.html",
    "title": "4.Microblocks & XGO: No Threshold! Journey of Robot Programming — keyestudio WiKi  documentation",
    "html_path": "/Users/david/david_project/知识库/microblock/download/bcb2858cea_4Microblocks__XGO_No_Threshold_Journey_of_Robot_Pr.html",
    "text_path": "/Users/david/david_project/知识库/microblock/download/bcb2858cea_4Microblocks__XGO_No_Threshold_Journey_of_Robot_Pr.txt",
    "filename_base": "bcb2858cea_4Microblocks__XGO_No_Threshold_Journey_of_Robot_Pr"
  },
  {
    "url": "https://events.canonical.com/event/89/contributions/470/attachments/260/376/MicroBlocks%20on%20Zephyr.pdf",
    "title": "No Title",
    "html_path": "/Users/david/david_project/知识库/microblock/download/86a94affd8_No_Title.html",
    "text_path": "/Users/david/david_project/知识库/microblock/download/86a94affd8_No_Title.txt",
    "filename_base": "86a94affd8_No_Title"
  },
  {
    "url": "https://flowus.cn/share/66c9bac7-3f27-44c4-9e32-19ca81643765",
    "title": "FlowUs æ¯æµï½ä¸ç«å¼ç¥è¯åä½ä¸åå¸å¹³å°",
    "html_path": "/Users/david/david_project/知识库/microblock/download/ee479d5bb9_FlowUs_ææµï½äçå¼çèåä½äååå¹³å.html",
    "text_path": "/Users/david/david_project/知识库/microblock/download/ee479d5bb9_FlowUs_ææµï½äçå¼çèåä½äååå¹³å.txt",
    "filename_base": "ee479d5bb9_FlowUs_ææµï½äçå¼çèåä½äååå¹³å"
  },
  {
    "url": "https://juejin.cn/post/7167674458415579143",
    "title": "比较图形化硬件编程平台在图形化硬件编程领域，出色的项目极少，上一个值得被批评的项目是微软的 MakeCode，迄今为止， - 掘金",
    "html_path": "/Users/david/david_project/知识库/microblock/download/6dcaab9014_比较图形化硬件编程平台在图形化硬件编程领域出色的项目极少上一个值得被批评的项目是微软的_MakeCo.html",
    "text_path": "/Users/david/david_project/知识库/microblock/download/6dcaab9014_比较图形化硬件编程平台在图形化硬件编程领域出色的项目极少上一个值得被批评的项目是微软的_MakeCo.txt",
    "filename_base": "6dcaab9014_比较图形化硬件编程平台在图形化硬件编程领域出色的项目极少上一个值得被批评的项目是微软的_MakeCo"
  },
  {
    "url": "https://juejin.cn/post/7167915712537690126",
    "title": "MicroBlocks 编程案例: 使用 micro:bit 接管 xlight彩虹灯很好看，小巧而明媚。 但我不想用它 - 掘金",
    "html_path": "/Users/david/david_project/知识库/microblock/download/8bd42621f1_MicroBlocks_编程案例_使用_microbit_接管_xlight彩虹灯很好看小巧而明媚.html",
    "text_path": "/Users/david/david_project/知识库/microblock/download/8bd42621f1_MicroBlocks_编程案例_使用_microbit_接管_xlight彩虹灯很好看小巧而明媚.txt",
    "filename_base": "8bd42621f1_MicroBlocks_编程案例_使用_microbit_接管_xlight彩虹灯很好看小巧而明媚"
  },
  {
    "url": "https://microblocks.fun/blog/2022-12-05-origins",
    "title": "The Origins of MicroBlocks - MicroBlocks",
    "html_path": "/Users/david/david_project/知识库/microblock/download/b79273fd83_The_Origins_of_MicroBlocks_-_MicroBlocks.html",
    "text_path": "/Users/david/david_project/知识库/microblock/download/b79273fd83_The_Origins_of_MicroBlocks_-_MicroBlocks.txt",
    "filename_base": "b79273fd83_The_Origins_of_MicroBlocks_-_MicroBlocks"
  },
  {
    "url": "https://microblocks.fun/what-is-microblocks",
    "title": "What is Microblocks - MicroBlocks",
    "html_path": "/Users/david/david_project/知识库/microblock/download/c8ea5e8829_What_is_Microblocks_-_MicroBlocks.html",
    "text_path": "/Users/david/david_project/知识库/microblock/download/c8ea5e8829_What_is_Microblocks_-_MicroBlocks.txt",
    "filename_base": "c8ea5e8829_What_is_Microblocks_-_MicroBlocks"
  },
  {
    "url": "https://microblocksfun.cn/about",
    "title": "About - ç©çè®¡ç®é¢åç Scratch - MicroBlocks ä¸­æä¸»é¡µ",
    "html_path": "/Users/david/david_project/知识库/microblock/download/323b0dc59b_About_-_ççèçéåç_Scratch_-_MicroBlocks_äæäéµ.html",
    "text_path": "/Users/david/david_project/知识库/microblock/download/323b0dc59b_About_-_ççèçéåç_Scratch_-_MicroBlocks_äæäéµ.txt",
    "filename_base": "323b0dc59b_About_-_ççèçéåç_Scratch_-_MicroBlocks_äæäéµ"
  },
  {
    "url": "https://microblocksfun.cn/blog/2024-11-18-MicroBlocks-in-China",
    "title": "MicroBlocks å¨ä¸­å½ - ç©çè®¡ç®é¢åç Scratch - MicroBlocks ä¸­æä¸»é¡µ",
    "html_path": "/Users/david/david_project/知识库/microblock/download/b79458e33e_MicroBlocks_åäå½_-_ççèçéåç_Scratch_-_MicroBlocks_ä.html",
    "text_path": "/Users/david/david_project/知识库/microblock/download/b79458e33e_MicroBlocks_åäå½_-_ççèçéåç_Scratch_-_MicroBlocks_ä.txt",
    "filename_base": "b79458e33e_MicroBlocks_åäå½_-_ççèçéåç_Scratch_-_MicroBlocks_ä"
  },
  {
    "url": "https://wiki.microblocks.fun/en/Tutorials/Intro_with_Boardie",
    "title": "Intro to MicroBlocks - Using BOARDIE | MicroBlocks Wiki",
    "html_path": "/Users/david/david_project/知识库/microblock/download/07b666f9b0_Intro_to_MicroBlocks_-_Using_BOARDIE__MicroBlocks.html",
    "text_path": "/Users/david/david_project/知识库/microblock/download/07b666f9b0_Intro_to_MicroBlocks_-_Using_BOARDIE__MicroBlocks.txt",
    "filename_base": "07b666f9b0_Intro_to_MicroBlocks_-_Using_BOARDIE__MicroBlocks"
  },
  {
    "url": "https://wiki.microblocks.fun/en/boards/supported",
    "title": "Board Guide | MicroBlocks Wiki",
    "html_path": "/Users/david/david_project/知识库/microblock/download/3a7e6987e5_Board_Guide__MicroBlocks_Wiki.html",
    "text_path": "/Users/david/david_project/知识库/microblock/download/3a7e6987e5_Board_Guide__MicroBlocks_Wiki.txt",
    "filename_base": "3a7e6987e5_Board_Guide__MicroBlocks_Wiki"
  },
  {
    "url": "https://wiki.seeedstudio.com/cn/xiao_esp32s3_microblocks/",
    "title": "MicroBlocks | Seeed Studio Wiki",
    "html_path": "/Users/david/david_project/知识库/microblock/download/6ad0a73a6f_MicroBlocks__Seeed_Studio_Wiki.html",
    "text_path": "/Users/david/david_project/知识库/microblock/download/6ad0a73a6f_MicroBlocks__Seeed_Studio_Wiki.txt",
    "filename_base": "6ad0a73a6f_MicroBlocks__Seeed_Studio_Wiki"
  },
  {
    "url": "https://www.beagleboard.org/blog/2024-06-25-microblocks-on-beagleconnect-freedom",
    "title": "MicroBlocks on BeagleConnect Freedom - BeagleBoard",
    "html_path": "/Users/david/david_project/知识库/microblock/download/b43f72eb84_MicroBlocks_on_BeagleConnect_Freedom_-_BeagleBoard.html",
    "text_path": "/Users/david/david_project/知识库/microblock/download/b43f72eb84_MicroBlocks_on_BeagleConnect_Freedom_-_BeagleBoard.txt",
    "filename_base": "b43f72eb84_MicroBlocks_on_BeagleConnect_Freedom_-_BeagleBoard"
  },
  {
    "url": "https://www.bilibili.com/opus/1009203897367003137",
    "title": "拥抱MicroBlocks：超简单的KittenBot葡萄板编程！ - 哔哩哔哩",
    "html_path": "/Users/david/david_project/知识库/microblock/download/a1e3fcded1_拥抱MicroBlocks超简单的KittenBot葡萄板编程_-_哔哩哔哩.html",
    "text_path": "/Users/david/david_project/知识库/microblock/download/a1e3fcded1_拥抱MicroBlocks超简单的KittenBot葡萄板编程_-_哔哩哔哩.txt",
    "filename_base": "a1e3fcded1_拥抱MicroBlocks超简单的KittenBot葡萄板编程_-_哔哩哔哩"
  }
]